streamlit_rockyroad_tools/__init__.py
streamlit_rockyroad_tools/st_breadcrumbs/__init__.py
streamlit_rockyroad_tools/st_breadcrumbs/example.py
streamlit_rockyroad_tools/st_breadcrumbs/frontend/build/asset-manifest.json
streamlit_rockyroad_tools/st_breadcrumbs/frontend/build/index.html
streamlit_rockyroad_tools/st_breadcrumbs/frontend/build/static/css/main.e395e190.css
streamlit_rockyroad_tools/st_breadcrumbs/frontend/build/static/css/main.e395e190.css.map
streamlit_rockyroad_tools/st_breadcrumbs/frontend/build/static/js/main.2abd8623.js
streamlit_rockyroad_tools/st_breadcrumbs/frontend/build/static/js/main.2abd8623.js.LICENSE.txt
streamlit_rockyroad_tools/st_breadcrumbs/frontend/build/static/js/main.2abd8623.js.map
streamlit_rockyroad_tools/st_download_base64/__init__.py
streamlit_rockyroad_tools/st_download_base64/download_base64_example.py
streamlit_rockyroad_tools/st_download_base64/frontend/build/asset-manifest.json
streamlit_rockyroad_tools/st_download_base64/frontend/build/index.html
streamlit_rockyroad_tools/st_download_base64/frontend/build/static/js/main.9ddcf37a.js
streamlit_rockyroad_tools/st_download_base64/frontend/build/static/js/main.9ddcf37a.js.LICENSE.txt
streamlit_rockyroad_tools/st_download_base64/frontend/build/static/js/main.9ddcf37a.js.map
streamlit_rockyroad_tools/st_download_tile/__init__.py
streamlit_rockyroad_tools/st_download_tile/download_tile_example.py
streamlit_rockyroad_tools/st_download_tile/frontend/build/asset-manifest.json
streamlit_rockyroad_tools/st_download_tile/frontend/build/index.html
streamlit_rockyroad_tools/st_download_tile/frontend/build/svg-sprite.svg
streamlit_rockyroad_tools/st_download_tile/frontend/build/static/css/main.3a6527d8.css
streamlit_rockyroad_tools/st_download_tile/frontend/build/static/css/main.3a6527d8.css.map
streamlit_rockyroad_tools/st_download_tile/frontend/build/static/js/main.350929d1.js
streamlit_rockyroad_tools/st_download_tile/frontend/build/static/js/main.350929d1.js.LICENSE.txt
streamlit_rockyroad_tools-0.0.48.dist-info/licenses/LICENSE
streamlit_rockyroad_tools-0.0.48.dist-info/METADATA
streamlit_rockyroad_tools-0.0.48.dist-info/WHEEL
streamlit_rockyroad_tools-0.0.48.dist-info/top_level.txt
streamlit_rockyroad_tools-0.0.48.dist-info/RECORD
